quantworks/ext/twitter/__init__.py
quantworks/ext/twitter/feed.py
quantworks_twitter-1.0.dist-info/WHEEL
quantworks_twitter-1.0.dist-info/METADATA
quantworks_twitter-1.0.dist-info/RECORD
